ganzoo/__init__.py
ganzoo/version.py
ganzoo/dcgan/__init__.py
ganzoo/dcgan/dcgan.py
ganzoo/gan/__init__.py
ganzoo/gan/gan.py
ganzoo/wgan/__init__.py
ganzoo/wgan/wgan.py
ganzoo/wgan_gp/__init__.py
ganzoo/wgan_gp/wgan_gp.py
ganzoo-0.0.1.dist-info/DESCRIPTION.rst
ganzoo-0.0.1.dist-info/METADATA
ganzoo-0.0.1.dist-info/RECORD
ganzoo-0.0.1.dist-info/WHEEL
ganzoo-0.0.1.dist-info/metadata.json
ganzoo-0.0.1.dist-info/top_level.txt
tests/__init__.py
tests/test_models.py
tests/test_preparation.py
