Metadata-Version: 2.0
Name: ganzoo
Version: 0.0.1
Summary: Implementation of all GANs
Home-page: https://github.com/innerlee/ganzoo
Author: Zhizhong Li
Author-email: 363664470@qq.com
License: MIT
Keywords: gan
Platform: UNKNOWN
Classifier: Development Status :: 4 - Beta
Classifier: License :: OSI Approved :: MIT License
Classifier: Operating System :: OS Independent
Classifier: Programming Language :: Python :: 3
Classifier: Programming Language :: Python :: 3.4
Classifier: Programming Language :: Python :: 3.5
Classifier: Programming Language :: Python :: 3.6
Classifier: Topic :: Utilities
Requires-Dist: numpy (>=1.11.1)
Requires-Dist: torch
Requires-Dist: torchvision
